cfug/__init__.py
cfug/__main__.py
cfug/command/__init__.py
cfug/command/build.py
cfug/command/clean.py
cfug/command/configure.py
cfug/command/new.py
cfug/command/test.py
cfug/exceptions.py
cfug/project.py
cfug/template/__init__.py
cfug/template/executable/CMakeLists.txt
cfug/template/executable/_editorconfig
cfug/template/executable/_gitignore
cfug/template/executable/ext/.cfugignore
cfug/template/executable/include/.cfugignore
cfug/template/executable/src/main.cpp
cfug/template/executable/test/CMakeLists.txt
cfug/template/executable/test/test_example.cpp
cfug/template/header-only/CMakeLists.txt
cfug/template/header-only/_editorconfig
cfug/template/header-only/_gitignore
cfug/template/header-only/cmake/ProjectConfig.cmake.in
cfug/template/header-only/include/.cfugignore
cfug/template/header-only/test/CMakeLists.txt
cfug/template/header-only/test/test_example.cpp
cfug/template/library/CMakeLists.txt
cfug/template/library/_editorconfig
cfug/template/library/_gitignore
cfug/template/library/include/.cfugignore
cfug/template/library/src/.cfugignore
cfug/template/library/test/CMakeLists.txt
cfug/template/library/test/test_example.cpp
cfug-0.1.1.dist-info/METADATA
cfug-0.1.1.dist-info/WHEEL
cfug-0.1.1.dist-info/entry_points.txt
cfug-0.1.1.dist-info/RECORD
