Metadata-Version: 2.1
Name: cfug
Version: 0.1.1
Summary: C++ project management utilities.
Home-page: https://github.com/RauliL/cfug
License: MIT
Author: Rauli Laine
Author-email: rauli.laine@iki.fi
Requires-Python: >=3.8.1,<4.0.0
Classifier: Development Status :: 3 - Alpha
Classifier: Intended Audience :: Developers
Classifier: License :: OSI Approved :: MIT License
Classifier: Operating System :: OS Independent
Classifier: Programming Language :: C++
Classifier: Programming Language :: Python :: 3
Classifier: Programming Language :: Python :: 3.9
Classifier: Programming Language :: Python :: 3.10
Classifier: Programming Language :: Python :: 3.11
Classifier: Programming Language :: Python :: 3.12
Classifier: Topic :: Software Development :: Build Tools
Classifier: Typing :: Typed
Requires-Dist: case-convertor (>=1.1.2,<2.0.0)
Requires-Dist: click (>=8.1.7,<9.0.0)
Requires-Dist: jinja2 (>=3.1.2,<4.0.0)
Requires-Dist: license (>=0.1a3,<0.2)
Requires-Dist: pathvalidate (>=3.2.0,<4.0.0)
Requires-Dist: pygit2 (>=1.13.3,<2.0.0)
Project-URL: Repository, https://github.com/RauliL/cfug
